mypackage/__init__.py
whateverpack-0.1.0.dist-info/LICENSE
whateverpack-0.1.0.dist-info/WHEEL
whateverpack-0.1.0.dist-info/METADATA
whateverpack-0.1.0.dist-info/RECORD
