Metadata-Version: 2.1
Name: whateverpack
Version: 0.1.0
Summary: hellp tests
License: MIT
Author: aahnik
Author-email: daw@aahnik.dev
Requires-Python: >=3.8,<4.0
Classifier: License :: OSI Approved :: MIT License
Classifier: Programming Language :: Python :: 3
Classifier: Programming Language :: Python :: 3.8
Classifier: Programming Language :: Python :: 3.9
